Metadata-Version: 1.1
Name: Flask-OpenID-Stateless
Version: 1.2.5
Summary: OpenID support for Flask, forked to make the library stateless.
Home-page: http://github.com/canonical-webteam/flask-openid/
Author: Canonical Web Team
Author-email: UNKNOWN
License: BSD
Platform: any
Classifier: Development Status :: 4 - Beta
Classifier: Environment :: Web Environment
Classifier: Intended Audience :: Developers
Classifier: License :: OSI Approved :: BSD License
Classifier: Operating System :: OS Independent
Classifier: Programming Language :: Python
Classifier: Topic :: Internet :: WWW/HTTP :: Dynamic Content
Classifier: Topic :: Software Development :: Libraries :: Python Modules
